<?xml version="1.0" encoding="utf-8"?>
<edmx:Edmx Version="4.0" xmlns:edmx="http://docs.oasis-open.org/odata/ns/edmx">
    <edmx:Reference Uri="../../catalogservice;v=2/Vocabularies(TechnicalName='%2FIWBEP%2FVOC_COMMON',Version='0001',SAP__Origin='LOCAL')/$value">
        <edmx:Include Namespace="com.sap.vocabularies.Common.v1" Alias="Common"/>
    </edmx:Reference>
    <edmx:Reference Uri="../../catalogservice;v=2/Vocabularies(TechnicalName='%2FIWBEP%2FVOC_UI',Version='0001',SAP__Origin='LOCAL')/$value">
        <edmx:Include Namespace="com.sap.vocabularies.UI.v1" Alias="UI"/>
    </edmx:Reference>
    <edmx:Reference Uri="../../catalogservice;v=2/Vocabularies(TechnicalName='%2FIWBEP%2FVOC_COMMUNICATION',Version='0001',SAP__Origin='LOCAL')/$value">
        <edmx:Include Namespace="com.sap.vocabularies.Communication.v1" Alias="Communication"/>
    </edmx:Reference>
    <edmx:Reference Uri="../../../sap/zotc_so_abc_check_srv/$metadata">
        <edmx:Include Namespace="ZOTC_SO_ABC_CHECK_SRV" Alias="SAP"/>
    </edmx:Reference>
    <edmx:DataServices>
        <Schema Namespace="zotc_so_abc_check_anno_mdl.v1" xmlns="http://docs.oasis-open.org/odata/ns/edm">
            <Annotations Target="ZOTC_SO_ABC_CHECK_SRV.ZOTC_C_SOABC_CHKType">
                <Annotation Term="UI.HeaderInfo">
                    <Record>
                        <PropertyValue Property="TypeName" String="Sales Order List Report"/>
                        <PropertyValue Property="TypeNamePlural" String="Sales Order"/>
                    </Record>
                </Annotation>
                <Annotation Term="UI.LineItem">
                    <Collection>
                        <Record Type="UI.DataField">
                            <PropertyValue Property="Value" Path="vbeln"/>
                        </Record>
                        <Record Type="UI.DataField">
                            <PropertyValue Property="Value" Path="kunnr"/>
                        </Record>
                        <Record Type="UI.DataField">
                            <PropertyValue Property="Value" Path="BusinessPartnerName"/>
                        </Record>
                        <Record Type="UI.DataField">
                            <PropertyValue Property="Value" Path="BusinessPartnerStreet"/>
                        </Record>
                        <Record Type="UI.DataField">
                            <PropertyValue Property="Value" Path="BusinessPartnerCity"/>
                        </Record>
                        <Record Type="UI.DataField">
                            <PropertyValue Property="Value" Path="BusinessPartnerPostalCode"/>
                        </Record>
                        <Record Type="UI.DataField">
                            <PropertyValue Property="Value" Path="BusinessPartnerCountry"/>
                        </Record>
                        <Record Type="UI.DataField">
                            <PropertyValue Property="Value" Path="BusinessPartnerRegion"/>
                        </Record>
                        <Record Type="UI.DataField">
                            <PropertyValue Property="Value" Path="vkorg"/>
                        </Record>
                        <Record Type="UI.DataField">
                            <PropertyValue Property="Value" Path="vtweg"/>
                        </Record>
                        <Record Type="UI.DataField">
                            <PropertyValue Property="Value" Path="spart"/>
                        </Record>
                        <Record Type="UI.DataField">
                            <PropertyValue Property="Value" Path="CustomerGroup"/>
                        </Record>
                        <Record Type="UI.DataField">
                            <PropertyValue Property="Value" Path="abgru"/>
                        </Record>
                        <Record Type="UI.DataField">
                            <PropertyValue Property="Value" Path="NextCheckDateforABC"/>
                        </Record>
                        <Record Type="UI.DataField">
                            <PropertyValue Property="Value" Path="NetValue"/>
                        </Record>
                        <Record Type="UI.DataField">
                            <PropertyValue Property="Value" Path="Currency"/>
                        </Record>
                        <Record Type="UI.DataField">
                            <PropertyValue Property="Value" Path="CreatedBy"/>
                        </Record>
                    </Collection>
                </Annotation>
                <Annotation Term="UI.SelectionFields">
                    <Collection>
                        <PropertyPath>kunnr</PropertyPath>
                        <PropertyPath>vkorg</PropertyPath>
                        <PropertyPath>vtweg</PropertyPath>
                        <PropertyPath>spart</PropertyPath>
                        <PropertyPath>CustomerGroup</PropertyPath>
                        <PropertyPath>vbeln</PropertyPath>
                        <PropertyPath>auart</PropertyPath>
                        <PropertyPath>audat</PropertyPath>
                        <PropertyPath>erdat</PropertyPath>
                        <PropertyPath>abgru</PropertyPath>
                    </Collection>
                </Annotation>
            </Annotations>
        </Schema>
    </edmx:DataServices>
</edmx:Edmx>